sympan/__init__.py
sympan/handlers.py
sympan-0.1.4.dist-info/METADATA
sympan-0.1.4.dist-info/WHEEL
sympan-0.1.4.dist-info/top_level.txt
sympan-0.1.4.dist-info/RECORD
