Metadata-Version: 2.1
Name: sympan
Version: 0.1.4
Summary: Small Python library for downloading the data from AWS S3
Home-page: http://www.github.com/~alem88/sympan/
Author: Alem Memic
Author-email: memicalem@gmail.com
License: MIT
Download-URL: https://github.com/alem88/sympan/archive/refs/tags/0.1.3.tar.gz
Platform: UNKNOWN
Classifier: Programming Language :: Python :: 3
Classifier: License :: OSI Approved :: MIT License
Classifier: Operating System :: OS Independent
Requires-Dist: boto3 (==1.15.18)
Requires-Dist: joblib (==1.0.1)
